CHANGES.txt
LICENSE.txt
MANIFEST.in
README.txt
setup.py
moleKule.egg-info/PKG-INFO
moleKule.egg-info/SOURCES.txt
moleKule.egg-info/dependency_links.txt
moleKule.egg-info/requires.txt
moleKule.egg-info/top_level.txt
molekule/__init__.py
molekule/render.py
molekule/structure.py
test/test_mol.py