Metadata-Version: 1.1
Name: moleKule
Version: 0.2.1
Summary: Python tool for molecule analysis.
Home-page: UNKNOWN
Author: M. Ezequiel Castillo
Author-email: ezecastillo@gmail.com
License: GPLv3
Keywords: molecule atom chemical structure
Platform: UNKNOWN
Classifier: Development Status :: 3 - Alpha
